jinjalive/__init__.py
jinjalive/_options.py
jinjalive/jinjalive.wsgi
jinjalive/console/__init__.py
jinjalive/console/cli.py
jinjalive/jinja/__init__.py
jinjalive/jinja/render.py
jinjalive/server/__init__.py
jinjalive/server/application.py
jinjalive/server/static/favicon.ico
jinjalive/server/static/bower/Qwigley/.bower.json
jinjalive/server/static/bower/Qwigley/7YaSO_TVGtx3eMdiqaA.ttf
jinjalive/server/static/bower/Qwigley/qwigley.css
jinjalive/server/static/bower/Raleway/.bower.json
jinjalive/server/static/bower/Raleway/raleway.css
jinjalive/server/static/bower/Raleway/tzj9b56b8RgXW8FAriS3USBnSvpkopQaUR-2r7iU.ttf
jinjalive/server/static/bower/RobotoMono/.bower.json
jinjalive/server/static/bower/RobotoMono/PNLsu_dywMa4C_DEpY50EAVxt0G0biEntp43Qt6E.ttf
jinjalive/server/static/bower/RobotoMono/robotoMono.css
jinjalive/server/static/bower/angular/.bower.json
jinjalive/server/static/bower/angular/README.md
jinjalive/server/static/bower/angular/angular-csp.css
jinjalive/server/static/bower/angular/angular.js
jinjalive/server/static/bower/angular/angular.min.js
jinjalive/server/static/bower/angular/angular.min.js.gzip
jinjalive/server/static/bower/angular/angular.min.js.map
jinjalive/server/static/bower/angular/bower.json
jinjalive/server/static/bower/angular/index.js
jinjalive/server/static/bower/angular/package.json
jinjalive/server/static/bower/angular-animate/.bower.json
jinjalive/server/static/bower/angular-animate/README.md
jinjalive/server/static/bower/angular-animate/angular-animate.js
jinjalive/server/static/bower/angular-animate/angular-animate.min.js
jinjalive/server/static/bower/angular-animate/angular-animate.min.js.map
jinjalive/server/static/bower/angular-animate/bower.json
jinjalive/server/static/bower/angular-animate/index.js
jinjalive/server/static/bower/angular-animate/package.json
jinjalive/server/static/bower/angular-bootstrap/.bower.json
jinjalive/server/static/bower/angular-bootstrap/.gitignore
jinjalive-0.2.0.dist-info/DESCRIPTION.rst
jinjalive-0.2.0.dist-info/METADATA
jinjalive-0.2.0.dist-info/RECORD
jinjalive-0.2.0.dist-info/WHEEL
jinjalive-0.2.0.dist-info/entry_points.txt
jinjalive-0.2.0.dist-info/metadata.json
jinjalive-0.2.0.dist-info/pbr.json
jinjalive-0.2.0.dist-info/top_level.txt
