Metadata-Version: 2.0
Name: jinjalive
Version: 0.2.0
Summary: JinjaLive: Jinja rendering made easy
Home-page: http://www.marlysys.com
Author: Marlysys
Author-email: rsaikali@marlysys.com
License: Apache
Platform: UNKNOWN
Classifier: Development Status :: 5 - Production/Stable
Classifier: Environment :: Console
Classifier: Environment :: Web Environment
Classifier: Framework :: Flask
Classifier: Intended Audience :: Developers
Classifier: Intended Audience :: System Administrators
Classifier: Topic :: Utilities
Classifier: Topic :: Software Development
Classifier: License :: OSI Approved :: Apache Software License
Classifier: Programming Language :: Python :: 2
Classifier: Programming Language :: Python :: 2.6
Classifier: Programming Language :: Python :: 2.7
Requires-Dist: Flask
Requires-Dist: Flask-Bower
Requires-Dist: Flask-Cache
Requires-Dist: Jinja2
Requires-Dist: PyYAML
Requires-Dist: Sphinx
Requires-Dist: oslo.config
Requires-Dist: oslo.log
